MANIFEST.in
README.rst
requirements.txt
setup.py
pyrouter/__init__.py
pyrouter/dispatcher.py
pyrouter/router.py
pyrouter.egg-info/PKG-INFO
pyrouter.egg-info/SOURCES.txt
pyrouter.egg-info/dependency_links.txt
pyrouter.egg-info/not-zip-safe
pyrouter.egg-info/requires.txt
pyrouter.egg-info/top_level.txt