Metadata-Version: 1.0
Name: pyrouter
Version: 1.0.0
Summary: Associate a request with the code that will convert it to a response
Home-page: https://github.com/felixcarmona/pyrouter
Author: Felix Carmona
Author-email: mail@felixcarmona.com
License: UNKNOWN
Platform: UNKNOWN
